{
  "schema_version": "foreman_bridge_v1",
  "updated_at": "2026-03-26 23:52 CDT",
  "directive_title": "PHASE 5.3A \u2014 DETERMINISTIC STRATEGY EVALUATION CONTRACT",
  "directive_status": "Active \u2014 Phase 5.3a deterministic strategy evaluation contract",
  "bridge_status": "developer_action_required",
  "next_actor": "developer",
  "reason": "Operator/Developer holds stick; complete Phase 5.3a work and proof; then hand off with the required phrase for architect review.",
  "handoff_phrase": "have cursor validate shared-docs",
  "proof_status": "missing",
  "architect_review_pending": false,
  "active_proof_section": null,
  "findings": [
    "phase 5.3a validator stub active; require architect code-and-proof review before closure"
  ],
  "recommended_next_directive": null,
  "last_foreman_result": "bridge",
  "source_files": [
    "docs/working/current_directive.md",
    "docs/working/shared_coordination_log.md"
  ]
}
