{
  "schema_version": "talking_stick_v1",
  "updated_at": "2026-03-26 20:45 CDT",
  "generation": "2026-03-26 20:45 CDT|PHASE 5.3B \u2014 STORED-DATA BACKTEST / SIMULATION LOOP|architect_action_required|architect|have the architect validate shared-docs",
  "holder": "architect",
  "handed_from": "developer",
  "handed_to": "architect",
  "reason": "Phase 5.3b proof present; architect validation next.",
  "required_phrase": "have the architect validate shared-docs",
  "directive_title": "PHASE 5.3B \u2014 STORED-DATA BACKTEST / SIMULATION LOOP"
}
